hsiboard/app.py
hsiboard/box.py
hsiboard/cmp.py
hsiboard/main.py
hsiboard/table.py
hsiboard/util.py
hsiboard/viewer.py
hsir/__init__.py
hsir/schedule.py
hsir/scheduler.py
hsir/trainer.py
hsir/data/__init__.py
hsir/data/dataloader.py
hsir/data/dataset.py
hsir/data/utils.py
hsir/data/sci/__init__.py
hsir/data/sci/dataset.py
hsir/data/ssr/__init__.py
hsir/data/ssr/dataset.py
hsir/data/transform/__init__.py
hsir/data/transform/general.py
hsir/data/transform/noise.py
hsir/data/transform/sr.py
hsir/model/__init__.py
hsir/model/denet.py
hsir/model/grunet.py
hsir/model/hsidcnn.py
hsir/model/memnet.py
hsir/model/restormer.py
hsir/model/uformer.py
hsir/model/unet3d.py
hsir/model/qrnn3d/__init__.py
hsir/model/qrnn3d/conv.py
hsir/model/qrnn3d/net.py
hsir/model/qrnn3d/qrnn.py
hsir/model/sci/__init__.py
hsir/model/sci/admm_net.py
hsir/model/sci/birnat.py
hsir/model/sci/cst.py
hsir/model/sci/dgsmp.py
hsir/model/sci/gap_net.py
hsir/model/sci/hdnet.py
hsir/model/sci/lambda_net.py
hsir/model/sci/mst.py
hsir/model/sci/mst_plus_plus.py
hsir/model/sci/tsa_net.py
hsir/model/sr/__init__.py
hsir/model/sr/mcnet.py
hsir/model/ssr/AWAN.py
hsir/model/ssr/HDNet.py
hsir/model/ssr/HSCNN_Plus.py
hsir/model/ssr/MIRNet.py
hsir/model/ssr/MPRNet.py
hsir/model/ssr/MST.py
hsir/model/ssr/MST_Plus_Plus.py
hsir/model/ssr/__init__.py
hsir/model/ssr/edsr.py
hsir/model/ssr/hinet.py
hsir/model/ssr/hrnet.py
hsir/model/t3sc/__init__.py
hsir/model/t3sc/base.py
hsir/model/t3sc/multilayer.py
hsir/model/t3sc/layers/__init__.py
hsir/model/t3sc/layers/encoding_layer.py
hsir/model/t3sc/layers/lowrank_sc_layer.py
hsir/model/t3sc/layers/soft_thresholding.py
hsir/model/t3sc/metrics/__init__.py
hsir/model/t3sc/metrics/metrics.py
hsir/model/t3sc/metrics/utils.py
hsir/model/t3sc/utils/__init__.py
hsir/model/t3sc/utils/patches_handler.py
hsirun/benchmark.py
hsirun/test.py
hsirun/train.py
hsirun/train_ssr.py
hsir-0.1.1.dist-info/LICENSE
hsir-0.1.1.dist-info/METADATA
hsir-0.1.1.dist-info/WHEEL
hsir-0.1.1.dist-info/top_level.txt
hsir-0.1.1.dist-info/RECORD
