Metadata-Version: 2.1
Name: hsir
Version: 0.1.1
Summary: Hyperspectral Image Restoration Toolbox
Home-page: https://github.com/Zeqiang-Lai/HSIR
License-File: LICENSE
Requires-Dist: tqdm
Requires-Dist: qqdm
Requires-Dist: timm
Requires-Dist: streamlit
Requires-Dist: torchlights
